odoo9_addon_stock_picking_package_preparation-9.0.1.0.0.99.dev16-py3.8-nspkg.pth
odoo_addons/stock_picking_package_preparation/README.rst
odoo_addons/stock_picking_package_preparation/__init__.py
odoo_addons/stock_picking_package_preparation/__openerp__.py
odoo_addons/stock_picking_package_preparation/i18n/de.po
odoo_addons/stock_picking_package_preparation/i18n/en.po
odoo_addons/stock_picking_package_preparation/i18n/es.po
odoo_addons/stock_picking_package_preparation/i18n/fr.po
odoo_addons/stock_picking_package_preparation/i18n/it.po
odoo_addons/stock_picking_package_preparation/i18n/sl.po
odoo_addons/stock_picking_package_preparation/i18n/stock_picking_package_preparation.pot
odoo_addons/stock_picking_package_preparation/model/__init__.py
odoo_addons/stock_picking_package_preparation/model/stock_picking_package_preparation.py
odoo_addons/stock_picking_package_preparation/security/ir.model.access.csv
odoo_addons/stock_picking_package_preparation/security/package_preparation_security.xml
odoo_addons/stock_picking_package_preparation/static/description/icon.png
odoo_addons/stock_picking_package_preparation/tests/__init__.py
odoo_addons/stock_picking_package_preparation/tests/test_package_preparation.py
odoo_addons/stock_picking_package_preparation/view/stock_picking_package_preparation_view.xml
odoo9_addon_stock_picking_package_preparation-9.0.1.0.0.99.dev16.dist-info/METADATA
odoo9_addon_stock_picking_package_preparation-9.0.1.0.0.99.dev16.dist-info/WHEEL
odoo9_addon_stock_picking_package_preparation-9.0.1.0.0.99.dev16.dist-info/namespace_packages.txt
odoo9_addon_stock_picking_package_preparation-9.0.1.0.0.99.dev16.dist-info/top_level.txt
odoo9_addon_stock_picking_package_preparation-9.0.1.0.0.99.dev16.dist-info/RECORD
